[
  {
    "id": 0,
    "searchText": "l*cia 七市 nanashi 20260221 date_y_2026 date_ym_2026_02  fallen goddess ",
    "searchSuggest": "Character\tL*cia\nDate\t2026/02\nCreator\t七市\nCreator\tNanashi"
  },
  {
    "id": 1,
    "searchText": "l*cia dorei 20260208 date_y_2026 date_ym_2026_02   ",
    "searchSuggest": "Character\tL*cia\nDate\t2026/02\nCreator\tDorei"
  },
  {
    "id": 2,
    "searchText": "l*cia mink 20251223 date_y_2025 date_ym_2025_12   ",
    "searchSuggest": "Character\tL*cia\nDate\t2025/12\nCreator\tMINK"
  },
  {
    "id": 3,
    "searchText": "l*cia 七市 nanashi 20250907 date_y_2025 date_ym_2025_09  predator tks",
    "searchSuggest": "Character\tL*cia\nDate\t2025/09\nCreator\t七市\nCreator\tNanashi\nKeyword\tTKS"
  },
  {
    "id": 4,
    "searchText": "l*cia  20250429 date_y_2025 date_ym_2025_04   ",
    "searchSuggest": "Character\tL*cia\nDate\t2025/04"
  },
  {
    "id": 5,
    "searchText": "l*cia 七市 nanashi 20250403 date_y_2025 date_ym_2025_04   tks",
    "searchSuggest": "Character\tL*cia\nDate\t2025/04\nCreator\t七市\nCreator\tNanashi\nKeyword\tTKS"
  },
  {
    "id": 6,
    "searchText": "l*cia 七市 nanashi 20250225 date_y_2025 date_ym_2025_02 https://files.catbox.moe/jzg8pe.jpg mating tks",
    "searchSuggest": "Character\tL*cia\nDate\t2025/02\nCreator\t七市\nCreator\tNanashi\nKeyword\tTKS"
  },
  {
    "id": 7,
    "searchText": "l*cia 温野りょく unoryoku 20250206 date_y_2025 date_ym_2025_02   tks",
    "searchSuggest": "Character\tL*cia\nDate\t2025/02\nCreator\t温野りょく\nCreator\tUnoRyoku\nKeyword\tTKS"
  },
  {
    "id": 8,
    "searchText": "l*cia 温野りょく unoryoku 20241031 date_y_2024 date_ym_2024_10  holy grail ",
    "searchSuggest": "Character\tL*cia\nDate\t2024/10\nCreator\t温野りょく\nCreator\tUnoRyoku"
  },
  {
    "id": 9,
    "searchText": "l*cia アタ ata 20241028 date_y_2024 date_ym_2024_10 https://www.youtube.com/watch?v=rtomolgignw  ",
    "searchSuggest": "Character\tL*cia\nDate\t2024/10\nCreator\tアタ\nCreator\tAta"
  },
  {
    "id": 10,
    "searchText": "l*cia mink 20240911 date_y_2024 date_ym_2024_09   ",
    "searchSuggest": "Character\tL*cia\nDate\t2024/09\nCreator\tMINK"
  },
  {
    "id": 11,
    "searchText": "l*cia 七市 nanashi 20240906 date_y_2024 date_ym_2024_09 https://www.fanbox.cc/@tks10ru/posts/8198807  tks",
    "searchSuggest": "Character\tL*cia\nDate\t2024/09\nCreator\t七市\nCreator\tNanashi\nKeyword\tTKS"
  },
  {
    "id": 12,
    "searchText": "l*cia aos 20240725 date_y_2024 date_ym_2024_07   ",
    "searchSuggest": "Character\tL*cia\nDate\t2024/07\nCreator\tAOS"
  },
  {
    "id": 13,
    "searchText": "l*cia dorei 20240620 date_y_2024 date_ym_2024_06   ",
    "searchSuggest": "Character\tL*cia\nDate\t2024/06\nCreator\tDorei"
  },
  {
    "id": 14,
    "searchText": "l*cia 七市 nanashi 20240515 date_y_2024 date_ym_2024_05  divine ecstasy ",
    "searchSuggest": "Character\tL*cia\nDate\t2024/05\nCreator\t七市\nCreator\tNanashi"
  },
  {
    "id": 15,
    "searchText": "l*cia yydap 20231109 date_y_2023 date_ym_2023_11   ",
    "searchSuggest": "Character\tL*cia\nDate\t2023/11\nCreator\tYYDAP"
  },
  {
    "id": 16,
    "searchText": "l*cia 七市 nanashi 20230706 date_y_2023 date_ym_2023_07 https://twitter.com/_ushiooo/status/1655551118964035584  ",
    "searchSuggest": "Character\tL*cia\nDate\t2023/07\nCreator\t七市\nCreator\tNanashi"
  },
  {
    "id": 17,
    "searchText": "l*cia 温野りょく unoryoku 20230617 date_y_2023 date_ym_2023_06   ",
    "searchSuggest": "Character\tL*cia\nDate\t2023/06\nCreator\t温野りょく\nCreator\tUnoRyoku"
  },
  {
    "id": 18,
    "searchText": "kanaut nishe q 20250930 date_y_2025 date_ym_2025_09   ",
    "searchSuggest": "Character\tKanaut Nishe\nDate\t2025/09\nCreator\tQ"
  },
  {
    "id": 19,
    "searchText": "kanaut nishe q 20250930 date_y_2025 date_ym_2025_09   ",
    "searchSuggest": "Character\tKanaut Nishe\nDate\t2025/09\nCreator\tQ"
  },
  {
    "id": 20,
    "searchText": "kanaut nishe 七市 nanashi 20250920 date_y_2025 date_ym_2025_09   ",
    "searchSuggest": "Character\tKanaut Nishe\nDate\t2025/09\nCreator\t七市\nCreator\tNanashi"
  },
  {
    "id": 21,
    "searchText": "kanaut nishe 中村六翅 nakamura rohane 20250320 date_y_2025 date_ym_2025_03   ",
    "searchSuggest": "Character\tKanaut Nishe\nDate\t2025/03\nCreator\t中村六翅\nCreator\tNakamura Rohane"
  },
  {
    "id": 22,
    "searchText": "kanaut nishe 中村六翅 nakamura rohane 20250124 date_y_2025 date_ym_2025_01   ",
    "searchSuggest": "Character\tKanaut Nishe\nDate\t2025/01\nCreator\t中村六翅\nCreator\tNakamura Rohane"
  },
  {
    "id": 23,
    "searchText": "kanaut nishe q 20241230 date_y_2024 date_ym_2024_12   ",
    "searchSuggest": "Character\tKanaut Nishe\nDate\t2024/12\nCreator\tQ"
  },
  {
    "id": 24,
    "searchText": "kanaut nishe q 20241230 date_y_2024 date_ym_2024_12   ",
    "searchSuggest": "Character\tKanaut Nishe\nDate\t2024/12\nCreator\tQ"
  },
  {
    "id": 25,
    "searchText": "kanaut nishe 七市 nanashi 20241130 date_y_2024 date_ym_2024_11 https://www.youtube.com/live/zpuckyalskw&t=17196  ",
    "searchSuggest": "Character\tKanaut Nishe\nDate\t2024/11\nCreator\t七市\nCreator\tNanashi"
  },
  {
    "id": 26,
    "searchText": "kanaut nishe q 20241027 date_y_2024 date_ym_2024_10 https://twitter.com/ukaisaki/status/1800480093405585416  ",
    "searchSuggest": "Character\tKanaut Nishe\nDate\t2024/10\nCreator\tQ"
  },
  {
    "id": 27,
    "searchText": "kanaut nishe q 20241027 date_y_2024 date_ym_2024_10   ",
    "searchSuggest": "Character\tKanaut Nishe\nDate\t2024/10\nCreator\tQ"
  },
  {
    "id": 28,
    "searchText": "kanaut nishe q 20240819 date_y_2024 date_ym_2024_08 https://twitter.com/ukaisaki/status/1429821364966346754  ",
    "searchSuggest": "Character\tKanaut Nishe\nDate\t2024/08\nCreator\tQ"
  },
  {
    "id": 29,
    "searchText": "kanaut nishe q 20240819 date_y_2024 date_ym_2024_08   ",
    "searchSuggest": "Character\tKanaut Nishe\nDate\t2024/08\nCreator\tQ"
  },
  {
    "id": 30,
    "searchText": "kanaut nishe dorei 20240406 date_y_2024 date_ym_2024_04   ",
    "searchSuggest": "Character\tKanaut Nishe\nDate\t2024/04\nCreator\tDorei"
  },
  {
    "id": 31,
    "searchText": "kanaut nishe aos 20240223 date_y_2024 date_ym_2024_02   ",
    "searchSuggest": "Character\tKanaut Nishe\nDate\t2024/02\nCreator\tAOS"
  },
  {
    "id": 32,
    "searchText": "kanaut nishe 島どうま shimadouma 20230405 date_y_2023 date_ym_2023_04   ",
    "searchSuggest": "Character\tKanaut Nishe\nDate\t2023/04\nCreator\t島どうま\nCreator\tShimaDouma"
  },
  {
    "id": 33,
    "searchText": "kanaut nishe もけ太 moketa 20230327 date_y_2023 date_ym_2023_03   ",
    "searchSuggest": "Character\tKanaut Nishe\nDate\t2023/03\nCreator\tもけ太\nCreator\tMoketa"
  },
  {
    "id": 34,
    "searchText": "kanaut nishe 温野りょく unoryoku 20230210 date_y_2023 date_ym_2023_02   ",
    "searchSuggest": "Character\tKanaut Nishe\nDate\t2023/02\nCreator\t温野りょく\nCreator\tUnoRyoku"
  },
  {
    "id": 35,
    "searchText": "kanaut nishe 七市 nanashi 20230129 date_y_2023 date_ym_2023_01   ",
    "searchSuggest": "Character\tKanaut Nishe\nDate\t2023/01\nCreator\t七市\nCreator\tNanashi"
  },
  {
    "id": 36,
    "searchText": "kanaut nishe gsus 20230113 date_y_2023 date_ym_2023_01   ",
    "searchSuggest": "Character\tKanaut Nishe\nDate\t2023/01\nCreator\tGSUS"
  },
  {
    "id": 37,
    "searchText": "kanaut nishe gisyu 20221211 date_y_2022 date_ym_2022_12   ",
    "searchSuggest": "Character\tKanaut Nishe\nDate\t2022/12\nCreator\tGisyu"
  },
  {
    "id": 38,
    "searchText": "kanaut nishe 七市 nanashi 20221113 date_y_2022 date_ym_2022_11 https://twitter.com/ukaisaki/status/1541606179650301953/  ",
    "searchSuggest": "Character\tKanaut Nishe\nDate\t2022/11\nCreator\t七市\nCreator\tNanashi"
  },
  {
    "id": 39,
    "searchText": "kanaut nishe gsus 20221106 date_y_2022 date_ym_2022_11   ",
    "searchSuggest": "Character\tKanaut Nishe\nDate\t2022/11\nCreator\tGSUS"
  },
  {
    "id": 40,
    "searchText": "kanaut nishe 温野りょく unoryoku 20220922 date_y_2022 date_ym_2022_09   ",
    "searchSuggest": "Character\tKanaut Nishe\nDate\t2022/09\nCreator\t温野りょく\nCreator\tUnoRyoku"
  },
  {
    "id": 41,
    "searchText": "studio k cityboy 20260225 date_y_2026 date_ym_2026_02   isj",
    "searchSuggest": "Character\tStudio K\nDate\t2026/02\nCreator\tcityboy\nKeyword\tisj"
  },
  {
    "id": 42,
    "searchText": "studio k 月 tsuki 20260220 date_y_2026 date_ym_2026_02   isj",
    "searchSuggest": "Character\tStudio K\nDate\t2026/02\nCreator\t月\nCreator\tTsuki\nKeyword\tisj"
  },
  {
    "id": 43,
    "searchText": "studio k  20251203 date_y_2025 date_ym_2025_12  sisters' love albemuth aru asu bema",
    "searchSuggest": "Character\tStudio K\nDate\t2025/12\nKeyword\tAlbemuth\nKeyword\tARU\nKeyword\tASU\nKeyword\tBEMA"
  },
  {
    "id": 44,
    "searchText": "studio k  20251122 date_y_2025 date_ym_2025_11  summer vacation 2 isj",
    "searchSuggest": "Character\tStudio K\nDate\t2025/11\nKeyword\tisj"
  },
  {
    "id": 45,
    "searchText": "studio k  20251001 date_y_2025 date_ym_2025_10  another welcome party albemuth aru asu bema",
    "searchSuggest": "Character\tStudio K\nDate\t2025/10\nKeyword\tAlbemuth\nKeyword\tARU\nKeyword\tASU\nKeyword\tBEMA"
  },
  {
    "id": 46,
    "searchText": "studio k  20250923 date_y_2025 date_ym_2025_09 https://twitter.com/issikiiiiiii2/status/1903408633108672912 summer vacation isj",
    "searchSuggest": "Character\tStudio K\nDate\t2025/09\nKeyword\tisj"
  },
  {
    "id": 47,
    "searchText": "studio k  20250919 date_y_2025 date_ym_2025_09   ciel",
    "searchSuggest": "Character\tStudio K\nDate\t2025/09\nKeyword\tCIEL"
  },
  {
    "id": 48,
    "searchText": "studio k bailikoi 20250820 date_y_2025 date_ym_2025_08   isj cosplay",
    "searchSuggest": "Character\tStudio K\nDate\t2025/08\nCreator\tBailikoi\nKeyword\tisj\nKeyword\tCosplay"
  },
  {
    "id": 49,
    "searchText": "studio k  20250802 date_y_2025 date_ym_2025_08   isj sekai",
    "searchSuggest": "Character\tStudio K\nDate\t2025/08\nKeyword\tisj\nKeyword\tSekai"
  },
  {
    "id": 50,
    "searchText": "studio k  20250602 date_y_2025 date_ym_2025_06  the harem 2 isj sekai",
    "searchSuggest": "Character\tStudio K\nDate\t2025/06\nKeyword\tisj\nKeyword\tSekai"
  },
  {
    "id": 51,
    "searchText": "studio k 中村六翅 nakamura rohane 20250322 date_y_2025 date_ym_2025_03 https://twitter.com/ritao_kamo/status/1894360728070701342  isj",
    "searchSuggest": "Character\tStudio K\nDate\t2025/03\nCreator\t中村六翅\nCreator\tNakamura Rohane\nKeyword\tisj"
  },
  {
    "id": 52,
    "searchText": "studio k 中村六翅 nakamura rohane 20250205 date_y_2025 date_ym_2025_02  luna isj",
    "searchSuggest": "Character\tStudio K\nDate\t2025/02\nCreator\t中村六翅\nCreator\tNakamura Rohane\nKeyword\tisj"
  },
  {
    "id": 53,
    "searchText": "studio k  20250124 date_y_2025 date_ym_2025_01  in a rush albemuth aru asu",
    "searchSuggest": "Character\tStudio K\nDate\t2025/01\nKeyword\tAlbemuth\nKeyword\tARU\nKeyword\tASU"
  },
  {
    "id": 54,
    "searchText": "studio k  20250117 date_y_2025 date_ym_2025_01  the harem isj sekai",
    "searchSuggest": "Character\tStudio K\nDate\t2025/01\nKeyword\tisj\nKeyword\tSekai"
  },
  {
    "id": 55,
    "searchText": "studio k 中村六翅 nakamura rohane 20241203 date_y_2024 date_ym_2024_12   isj",
    "searchSuggest": "Character\tStudio K\nDate\t2024/12\nCreator\t中村六翅\nCreator\tNakamura Rohane\nKeyword\tisj"
  },
  {
    "id": 56,
    "searchText": "studio k  20241126 date_y_2024 date_ym_2024_11  remote ecstasy ciel",
    "searchSuggest": "Character\tStudio K\nDate\t2024/11\nKeyword\tCIEL"
  },
  {
    "id": 57,
    "searchText": "studio k  20240729 date_y_2024 date_ym_2024_07 https://twitter.com/yoneyamai/status/1726414184596775337/ forget me not albemuth aru asu",
    "searchSuggest": "Character\tStudio K\nDate\t2024/07\nKeyword\tAlbemuth\nKeyword\tARU\nKeyword\tASU"
  },
  {
    "id": 58,
    "searchText": "studio k  20240726 date_y_2024 date_ym_2024_07  welcome party ciel",
    "searchSuggest": "Character\tStudio K\nDate\t2024/07\nKeyword\tCIEL"
  },
  {
    "id": 59,
    "searchText": "studio k  20240513 date_y_2024 date_ym_2024_05   ciel",
    "searchSuggest": "Character\tStudio K\nDate\t2024/05\nKeyword\tCIEL"
  },
  {
    "id": 60,
    "searchText": "studio k  20240423 date_y_2024 date_ym_2024_04   ciel isj",
    "searchSuggest": "Character\tStudio K\nDate\t2024/04\nKeyword\tCIEL\nKeyword\tisj"
  },
  {
    "id": 61,
    "searchText": "studio k 中村六翅 nakamura rohane 20240410 date_y_2024 date_ym_2024_04   isj",
    "searchSuggest": "Character\tStudio K\nDate\t2024/04\nCreator\t中村六翅\nCreator\tNakamura Rohane\nKeyword\tisj"
  },
  {
    "id": 62,
    "searchText": "studio k  20240225 date_y_2024 date_ym_2024_02   ciel",
    "searchSuggest": "Character\tStudio K\nDate\t2024/02\nKeyword\tCIEL"
  },
  {
    "id": 63,
    "searchText": "studio k 中村六翅 nakamura rohane 20240113 date_y_2024 date_ym_2024_01   isj",
    "searchSuggest": "Character\tStudio K\nDate\t2024/01\nCreator\t中村六翅\nCreator\tNakamura Rohane\nKeyword\tisj"
  },
  {
    "id": 64,
    "searchText": "studio k  20231215 date_y_2023 date_ym_2023_12  parallel canvas ii isj",
    "searchSuggest": "Character\tStudio K\nDate\t2023/12\nKeyword\tisj"
  },
  {
    "id": 65,
    "searchText": "studio k  20231117 date_y_2023 date_ym_2023_11  happy 4th anniv. isj",
    "searchSuggest": "Character\tStudio K\nDate\t2023/11\nKeyword\tisj"
  },
  {
    "id": 66,
    "searchText": "studio k  20231018 date_y_2023 date_ym_2023_10 https://twitter.com/yoneyamai/status/1726413893201768591/ 1st album release albemuth aru asu",
    "searchSuggest": "Character\tStudio K\nDate\t2023/10\nKeyword\tAlbemuth\nKeyword\tARU\nKeyword\tASU"
  },
  {
    "id": 67,
    "searchText": "studio k  20230924 date_y_2023 date_ym_2023_09   ciel",
    "searchSuggest": "Character\tStudio K\nDate\t2023/09\nKeyword\tCIEL"
  },
  {
    "id": 68,
    "searchText": "studio k  20230917 date_y_2023 date_ym_2023_09 https://twitter.com/asu_virtual/status/1561669519914938368  albemuth aru asu",
    "searchSuggest": "Character\tStudio K\nDate\t2023/09\nKeyword\tAlbemuth\nKeyword\tARU\nKeyword\tASU"
  },
  {
    "id": 69,
    "searchText": "azki gisyu 20260125 date_y_2026 date_ym_2026_01   tokino sora",
    "searchSuggest": "Character\tAZKi\nDate\t2026/01\nCreator\tGisyu\nKeyword\tTokino Sora"
  },
  {
    "id": 70,
    "searchText": "azki q 20250302 date_y_2025 date_ym_2025_03   ",
    "searchSuggest": "Character\tAZKi\nDate\t2025/03\nCreator\tQ"
  },
  {
    "id": 71,
    "searchText": "azki q 20250302 date_y_2025 date_ym_2025_03   ",
    "searchSuggest": "Character\tAZKi\nDate\t2025/03\nCreator\tQ"
  },
  {
    "id": 72,
    "searchText": "azki gisyu 20240421 date_y_2024 date_ym_2024_04   kazama iroha",
    "searchSuggest": "Character\tAZKi\nDate\t2024/04\nCreator\tGisyu\nKeyword\tKazama Iroha"
  },
  {
    "id": 73,
    "searchText": "azki gisyu 20240421 date_y_2024 date_ym_2024_04   kazama iroha",
    "searchSuggest": "Character\tAZKi\nDate\t2024/04\nCreator\tGisyu\nKeyword\tKazama Iroha"
  },
  {
    "id": 74,
    "searchText": "azki 雪国裕 yukiguniyuu 20240409 date_y_2024 date_ym_2024_04   ",
    "searchSuggest": "Character\tAZKi\nDate\t2024/04\nCreator\t雪国裕\nCreator\tYukiguniYuu"
  },
  {
    "id": 75,
    "searchText": "azki 七市 nanashi 20240114 date_y_2024 date_ym_2024_01   tokino sora",
    "searchSuggest": "Character\tAZKi\nDate\t2024/01\nCreator\t七市\nCreator\tNanashi\nKeyword\tTokino Sora"
  },
  {
    "id": 76,
    "searchText": "azki 桃萌百 momomo momo 20240106 date_y_2024 date_ym_2024_01  geoguessr ",
    "searchSuggest": "Character\tAZKi\nDate\t2024/01\nCreator\t桃萌百\nCreator\tMomomo Momo"
  },
  {
    "id": 77,
    "searchText": "azki 流し満貫 naga4mangan 20231231 date_y_2023 date_ym_2023_12   ",
    "searchSuggest": "Character\tAZKi\nDate\t2023/12\nCreator\t流し満貫\nCreator\tNaga4mangan"
  },
  {
    "id": 78,
    "searchText": "azki もけ太 moketa 20230914 date_y_2023 date_ym_2023_09   ",
    "searchSuggest": "Character\tAZKi\nDate\t2023/09\nCreator\tもけ太\nCreator\tMoketa"
  },
  {
    "id": 79,
    "searchText": "azki 温野りょく unoryoku 20230912 date_y_2023 date_ym_2023_09   ",
    "searchSuggest": "Character\tAZKi\nDate\t2023/09\nCreator\t温野りょく\nCreator\tUnoRyoku"
  },
  {
    "id": 80,
    "searchText": "azki アタ ata 20230702 date_y_2023 date_ym_2023_07   tokino sora",
    "searchSuggest": "Character\tAZKi\nDate\t2023/07\nCreator\tアタ\nCreator\tAta\nKeyword\tTokino Sora"
  },
  {
    "id": 81,
    "searchText": "azki うたゆうか yuukauta 20230603 date_y_2023 date_ym_2023_06   tokino sora",
    "searchSuggest": "Character\tAZKi\nDate\t2023/06\nCreator\tうたゆうか\nCreator\tYuukaUta\nKeyword\tTokino Sora"
  },
  {
    "id": 82,
    "searchText": "azki 病ん太廊 yantaro 20230527 date_y_2023 date_ym_2023_05   tokino sora",
    "searchSuggest": "Character\tAZKi\nDate\t2023/05\nCreator\t病ん太廊\nCreator\tYantaro\nKeyword\tTokino Sora"
  },
  {
    "id": 83,
    "searchText": "n*yuta 七市 nanashi 20250608 date_y_2025 date_ym_2025_06   natsume itsuki aitsuki nakuru",
    "searchSuggest": "Character\tn*yuta\nDate\t2025/06\nCreator\t七市\nCreator\tNanashi\nKeyword\tNatsume Itsuki\nKeyword\tAitsuki Nakuru"
  },
  {
    "id": 84,
    "searchText": "n*yuta 七市 nanashi 20241231 date_y_2024 date_ym_2024_12   natsume itsuki aitsuki nakuru",
    "searchSuggest": "Character\tn*yuta\nDate\t2024/12\nCreator\t七市\nCreator\tNanashi\nKeyword\tNatsume Itsuki\nKeyword\tAitsuki Nakuru"
  },
  {
    "id": 85,
    "searchText": "n*yuta  20241208 date_y_2024 date_ym_2024_12 https://twitter.com/7utauta/status/1839664172331864348 17th album release ",
    "searchSuggest": "Character\tn*yuta\nDate\t2024/12"
  },
  {
    "id": 86,
    "searchText": "n*yuta 七市 nanashi 20231031 date_y_2023 date_ym_2023_10   ",
    "searchSuggest": "Character\tn*yuta\nDate\t2023/10\nCreator\t七市\nCreator\tNanashi"
  },
  {
    "id": 87,
    "searchText": "n*yuta 七市 nanashi 20230830 date_y_2023 date_ym_2023_08   natsume itsuki aitsuki nakuru",
    "searchSuggest": "Character\tn*yuta\nDate\t2023/08\nCreator\t七市\nCreator\tNanashi\nKeyword\tNatsume Itsuki\nKeyword\tAitsuki Nakuru"
  },
  {
    "id": 88,
    "searchText": "h*nabasami kyo asumi 20240918 date_y_2024 date_ym_2024_09   ",
    "searchSuggest": "Character\tH*nabasami Kyo\nDate\t2024/09\nCreator\tAsuMi"
  },
  {
    "id": 89,
    "searchText": "h*nabasami kyo 温野りょく unoryoku 20231204 date_y_2023 date_ym_2023_12   ",
    "searchSuggest": "Character\tH*nabasami Kyo\nDate\t2023/12\nCreator\t温野りょく\nCreator\tUnoRyoku"
  },
  {
    "id": 90,
    "searchText": "h*nabasami kyo うたゆうか yuukauta 20231006 date_y_2023 date_ym_2023_10   ",
    "searchSuggest": "Character\tH*nabasami Kyo\nDate\t2023/10\nCreator\tうたゆうか\nCreator\tYuukaUta"
  },
  {
    "id": 91,
    "searchText": "k*toha 温野りょく unoryoku 20240102 date_y_2024 date_ym_2024_01   ",
    "searchSuggest": "Character\tK*toha\nDate\t2024/01\nCreator\t温野りょく\nCreator\tUnoRyoku"
  },
  {
    "id": 92,
    "searchText": "k*toha かりうめ kariume 20231204 date_y_2023 date_ym_2023_12   ",
    "searchSuggest": "Character\tK*toha\nDate\t2023/12\nCreator\tかりうめ\nCreator\tKariume"
  },
  {
    "id": 93,
    "searchText": "hachi 七市 nanashi 20240405 date_y_2024 date_ym_2024_04   ",
    "searchSuggest": "Character\tHACHI\nDate\t2024/04\nCreator\t七市\nCreator\tNanashi"
  },
  {
    "id": 94,
    "searchText": "blue archive 中村六翅 nakamura rohane 20241223 date_y_2024 date_ym_2024_12   ",
    "searchSuggest": "Character\tBlue Archive\nDate\t2024/12\nCreator\t中村六翅\nCreator\tNakamura Rohane"
  },
  {
    "id": 95,
    "searchText": "blue archive 中村六翅 nakamura rohane 20230808 date_y_2023 date_ym_2023_08   ",
    "searchSuggest": "Character\tBlue Archive\nDate\t2023/08\nCreator\t中村六翅\nCreator\tNakamura Rohane"
  },
  {
    "id": 96,
    "searchText": "blue archive 中村六翅 nakamura rohane 20230613 date_y_2023 date_ym_2023_06   ",
    "searchSuggest": "Character\tBlue Archive\nDate\t2023/06\nCreator\t中村六翅\nCreator\tNakamura Rohane"
  },
  {
    "id": 97,
    "searchText": "ninomae ina'nis 七市 nanashi 20230629 date_y_2023 date_ym_2023_06   ",
    "searchSuggest": "Character\tNinomae Ina'nis\nDate\t2023/06\nCreator\t七市\nCreator\tNanashi"
  },
  {
    "id": 98,
    "searchText": "ninomae ina'nis 七市 nanashi 20220915 date_y_2022 date_ym_2022_09   ",
    "searchSuggest": "Character\tNinomae Ina'nis\nDate\t2022/09\nCreator\t七市\nCreator\tNanashi"
  },
  {
    "id": 99,
    "searchText": "ninomae ina'nis 紫信号 signalviolet 20220817 date_y_2022 date_ym_2022_08   ",
    "searchSuggest": "Character\tNinomae Ina'nis\nDate\t2022/08\nCreator\t紫信号\nCreator\tSignalViolet"
  },
  {
    "id": 100,
    "searchText": "ninomae ina'nis うたゆうか yuukauta 20220806 date_y_2022 date_ym_2022_08   ",
    "searchSuggest": "Character\tNinomae Ina'nis\nDate\t2022/08\nCreator\tうたゆうか\nCreator\tYuukaUta"
  },
  {
    "id": 101,
    "searchText": "tokomachi 病ん太廊 yantaro 20220824 date_y_2022 date_ym_2022_08   hoshimachi suisei inui toko",
    "searchSuggest": "Character\tTokomachi\nDate\t2022/08\nCreator\t病ん太廊\nCreator\tYantaro\nKeyword\tHoshimachi Suisei\nKeyword\tInui Toko"
  },
  {
    "id": 102,
    "searchText": "tokomachi けーえぬ keienu 20220712 date_y_2022 date_ym_2022_07   hoshimachi suisei inui toko",
    "searchSuggest": "Character\tTokomachi\nDate\t2022/07\nCreator\tけーえぬ\nCreator\tKeieNu\nKeyword\tHoshimachi Suisei\nKeyword\tInui Toko"
  },
  {
    "id": 103,
    "searchText": "tokomachi うたゆうか yuukauta 20220611 date_y_2022 date_ym_2022_06   hoshimachi suisei inui toko",
    "searchSuggest": "Character\tTokomachi\nDate\t2022/06\nCreator\tうたゆうか\nCreator\tYuukaUta\nKeyword\tHoshimachi Suisei\nKeyword\tInui Toko"
  },
  {
    "id": 104,
    "searchText": "tokomachi 病ん太廊 yantaro 20220427 date_y_2022 date_ym_2022_04   hoshimachi suisei inui toko",
    "searchSuggest": "Character\tTokomachi\nDate\t2022/04\nCreator\t病ん太廊\nCreator\tYantaro\nKeyword\tHoshimachi Suisei\nKeyword\tInui Toko"
  },
  {
    "id": 105,
    "searchText": "tokomachi u枝z狼 uedazirou 20220227 date_y_2022 date_ym_2022_02   hoshimachi suisei inui toko",
    "searchSuggest": "Character\tTokomachi\nDate\t2022/02\nCreator\tU枝Z狼\nCreator\tUedazirou\nKeyword\tHoshimachi Suisei\nKeyword\tInui Toko"
  },
  {
    "id": 106,
    "searchText": "tokomachi アタ ata 20211225 date_y_2021 date_ym_2021_12   hoshimachi suisei inui toko",
    "searchSuggest": "Character\tTokomachi\nDate\t2021/12\nCreator\tアタ\nCreator\tAta\nKeyword\tHoshimachi Suisei\nKeyword\tInui Toko"
  },
  {
    "id": 107,
    "searchText": "tokomachi 病ん太廊 yantaro 20211209 date_y_2021 date_ym_2021_12   hoshimachi suisei inui toko",
    "searchSuggest": "Character\tTokomachi\nDate\t2021/12\nCreator\t病ん太廊\nCreator\tYantaro\nKeyword\tHoshimachi Suisei\nKeyword\tInui Toko"
  },
  {
    "id": 108,
    "searchText": "tokomachi pukara 20211208 date_y_2021 date_ym_2021_12   hoshimachi suisei inui toko",
    "searchSuggest": "Character\tTokomachi\nDate\t2021/12\nCreator\tPUKARA\nKeyword\tHoshimachi Suisei\nKeyword\tInui Toko"
  },
  {
    "id": 109,
    "searchText": "tokomachi asumi 20211114 date_y_2021 date_ym_2021_11   hoshimachi suisei",
    "searchSuggest": "Character\tTokomachi\nDate\t2021/11\nCreator\tAsuMi\nKeyword\tHoshimachi Suisei"
  },
  {
    "id": 110,
    "searchText": "tokomachi 病ん太廊 yantaro 20211113 date_y_2021 date_ym_2021_11   hoshimachi suisei inui toko",
    "searchSuggest": "Character\tTokomachi\nDate\t2021/11\nCreator\t病ん太廊\nCreator\tYantaro\nKeyword\tHoshimachi Suisei\nKeyword\tInui Toko"
  },
  {
    "id": 111,
    "searchText": "tokomachi 温野りょく unoryoku 20211102 date_y_2021 date_ym_2021_11   hoshimachi suisei inui toko",
    "searchSuggest": "Character\tTokomachi\nDate\t2021/11\nCreator\t温野りょく\nCreator\tUnoRyoku\nKeyword\tHoshimachi Suisei\nKeyword\tInui Toko"
  },
  {
    "id": 112,
    "searchText": "tokomachi 病ん太廊 yantaro 20210918 date_y_2021 date_ym_2021_09   hoshimachi suisei",
    "searchSuggest": "Character\tTokomachi\nDate\t2021/09\nCreator\t病ん太廊\nCreator\tYantaro\nKeyword\tHoshimachi Suisei"
  },
  {
    "id": 113,
    "searchText": "tokomachi jungle 20210909 date_y_2021 date_ym_2021_09   hoshimachi suisei inui toko",
    "searchSuggest": "Character\tTokomachi\nDate\t2021/09\nCreator\tJUNGLE\nKeyword\tHoshimachi Suisei\nKeyword\tInui Toko"
  },
  {
    "id": 114,
    "searchText": "tokomachi 温野りょく unoryoku 20210706 date_y_2021 date_ym_2021_07   hoshimachi suisei",
    "searchSuggest": "Character\tTokomachi\nDate\t2021/07\nCreator\t温野りょく\nCreator\tUnoRyoku\nKeyword\tHoshimachi Suisei"
  },
  {
    "id": 115,
    "searchText": "tokomachi 病ん太廊 yantaro 20210514 date_y_2021 date_ym_2021_05   hoshimachi suisei inui toko",
    "searchSuggest": "Character\tTokomachi\nDate\t2021/05\nCreator\t病ん太廊\nCreator\tYantaro\nKeyword\tHoshimachi Suisei\nKeyword\tInui Toko"
  },
  {
    "id": 116,
    "searchText": "tokomachi 病ん太廊 yantaro 20210411 date_y_2021 date_ym_2021_04   hoshimachi suisei",
    "searchSuggest": "Character\tTokomachi\nDate\t2021/04\nCreator\t病ん太廊\nCreator\tYantaro\nKeyword\tHoshimachi Suisei"
  },
  {
    "id": 117,
    "searchText": "tokomachi 病ん太廊 yantaro 20210321 date_y_2021 date_ym_2021_03   hoshimachi suisei inui toko",
    "searchSuggest": "Character\tTokomachi\nDate\t2021/03\nCreator\t病ん太廊\nCreator\tYantaro\nKeyword\tHoshimachi Suisei\nKeyword\tInui Toko"
  },
  {
    "id": 118,
    "searchText": "tokomachi 病ん太廊 yantaro 20201220 date_y_2020 date_ym_2020_12   hoshimachi suisei",
    "searchSuggest": "Character\tTokomachi\nDate\t2020/12\nCreator\t病ん太廊\nCreator\tYantaro\nKeyword\tHoshimachi Suisei"
  }
]
